ledregulator/__init__.py
ledregulator/led_sequence.cfg
ledregulator/main.py
ledregulator/runserver.py
ledregulator-0.14.0.dist-info/entry_points.txt
ledregulator-0.14.0.dist-info/WHEEL
ledregulator-0.14.0.dist-info/METADATA
ledregulator-0.14.0.dist-info/RECORD
